{
  "path": "lib",
  "widgetbook": true,
  "styles": {
    "inset": 8.0,
    "colors": {
      "primary": "#1473E6",
      "accent": {
        "50": "#EFEFEF",
        "100": "#C8C8C8",
        "200": "#A2A2A2",
        "300": "#858585",
        "400": "#7A7A7A",
        "500": "#494949",
        "600": "#333333",
        "700": "#2F2F2F",
        "800": "#1E1E1E",
        "900": "#1A1A1A"
      },
      "red": {
        "50": "#EC5B62",
        "100": "#B30B00"
      },
      "border": {
        "default": "#333333",
        "strong": "#C8C8C8",
        "weak": "#494949"
      },
      "bg": {
        "default": "#1A1A1A",
        "weak": "#1E1E1E",
        "hover": "#2F2F2F"
      },
      "icon": {
        "default": "#A2A2A2",
        "weak": "#7A7A7A",
        "strong": "#EFEFEF"
      },
      "text": {
        "default": "#C8C8C8",
        "weak": "#858585",
        "strong": "#EFEFEF"
      },
      "buttonText": "#C8C8C8",
      "buttonBorder": "#C8C8C8"
    }
  },
  "components": [
    "lib/styles/styles.dart",
    "lib/styles/ui_colors.dart",
    "lib/styles/ui_insets.dart",
    "lib/widgetbook/widgetbook_app.dart",
    "lib/widgetbook/widgetbook_components.dart"
  ]
}